kivy_deps/__init__.py
kivy_deps/glew_dev/__init__.py
kivy_deps.glew_dev-0.3.1.data/data/include/GL/eglew.h
kivy_deps.glew_dev-0.3.1.data/data/include/GL/glew.h
kivy_deps.glew_dev-0.3.1.data/data/include/GL/glxew.h
kivy_deps.glew_dev-0.3.1.data/data/include/GL/wglew.h
kivy_deps.glew_dev-0.3.1.data/data/libs/glew32.lib
kivy_deps.glew_dev-0.3.1.dist-info/METADATA
kivy_deps.glew_dev-0.3.1.dist-info/WHEEL
kivy_deps.glew_dev-0.3.1.dist-info/top_level.txt
kivy_deps.glew_dev-0.3.1.dist-info/RECORD
