Metadata-Version: 2.1
Name: kivy-deps.glew-dev
Version: 0.3.1
Summary: Repackaged binary dependency of Kivy.
Home-page: http://kivy.org/
Author: Kivy Crew
Author-email: kivy-dev@googlegroups.com
License: MIT
Platform: UNKNOWN
